task 1/program_counter/program_counter.sv
module program_counter (output logic [31:0] PC, PCPlus4,
                        input logic [31:0] PCTarget, ALUResult,
                        input logic [1:0] PCSrc, 
                        input logic Reset, CLK);

logic [31:0] PCNext;

assign PCPlus4 = PC + 4;

always_comb begin
    case (PCSrc)
        2'b00: PCNext = PCPlus4;
        2'b01: PCNext = PCTarget;
        2'b10: PCNext = ALUResult;
        default: PCNext = 32'd0;
    endcase
end

always_ff @ (posedge CLK) begin
    if (Reset) PC <= 32'd0;
    else PC <= PCNext;
end

endmodule

program_counter/program_counter_tb.sv
`timescale 1ns/1ps  // Define Time Units
`include "program_counter.sv"  // Include the module under test

module program_counter_tb;

// Declare test variables
logic [31:0] t_PC, t_PCPlus4, t_PCTarget, t_ALUResult;
logic [1:0] t_PCSrc;
logic t_Reset, t_CLK;

// Instantiate the module under test (DUT)
program_counter dut(
    .PC(t_PC),
    .PCPlus4(t_PCPlus4),
    .PCTarget(t_PCTarget),
    .ALUResult(t_ALUResult),
    .PCSrc(t_PCSrc),
    .Reset(t_Reset),
    .CLK(t_CLK)
);

// sets the clock
initial begin
    t_CLK = 1;
    // Loop for t_CLK
    for (int i = 0; i < 40; i++) begin
        #5 t_CLK = ~t_CLK;
    end
end

initial begin
    // Create a waveform dump file for GTKWave analysis
    $dumpfile("program_counter_tb.vcd"); 
    $dumpvars(0, program_counter_tb);
    
    t_PCSrc = 2'b00;  // Default to normal execution
    t_Reset = 1;  // Apply reset
    #10;
    t_Reset = 0;  // Release reset
    #10;

    $display("Starting Program Counter Tests...");

    // Test Case 1: Normal Execution (PCSrc = 00, PC increments by 4)
    $display("Normal Execution: PC increments by 4");
    t_PCSrc = 2'b00;
    #40;

    // Test Case 2: Branch Taken (PCSrc = 01, PC = PCTarget)
    $display("Branch Taken: PC = PCTarget");
    t_PCTarget = 32'h00000050; // Example branch target
    t_PCSrc = 2'b01;
    #10;
    t_PCSrc = 2'b00;  // Reset to normal execution
    #30;

    $display("Jump: PC = ALUResult");
    // Test Case 3: Jump (PCSrc = 10, PC = ALUResult)
    t_ALUResult = 32'h00000100; // Example jump target
    t_PCSrc = 2'b10;
    #10;
    t_PCSrc = 2'b00;  // Reset to normal execution
    #20

    $display("Reset the counter to 0");
    // Test Case 4: Reset Condition
    t_Reset = 1;
    #10;
    t_Reset = 0;
    #10;

    $finish;
end

// Generate Clock Signal
// always #5 t_CLK = ~t_CLK;  // Toggle clock every 5ns

// Monitor changes in signals
initial begin
    $monitor("Time = %3d, PCSrc = %b, PC = %h, PCPlus4 = %h, PCTarget = %h, ALUResult = %h, Reset = %b", 
             $time, t_PCSrc, t_PC, t_PCPlus4, t_PCTarget, t_ALUResult, t_Reset);
end

endmodule

task 1/program_counter/program_counter_tb.vcd
$date
	Sun Mar 09 15:38:28 2025
$end
$version
	Icarus Verilog
$end
$timescale
	1ps
$end
$scope module program_counter_tb $end
$var wire 32 ! t_PCPlus4 [31:0] $end
$var wire 32 " t_PC [31:0] $end
$var reg 32 # t_ALUResult [31:0] $end
$var reg 1 $ t_CLK $end
$var reg 2 % t_PCSrc [1:0] $end
$var reg 32 & t_PCTarget [31:0] $end
$var reg 1 ' t_Reset $end
$scope module dut $end
$var wire 32 ( ALUResult [31:0] $end
$var wire 1 $ CLK $end
$var wire 2 ) PCSrc [1:0] $end
$var wire 32 * PCTarget [31:0] $end
$var wire 1 ' Reset $end
$var wire 32 + PCPlus4 [31:0] $end
$var reg 32 , PC [31:0] $end
$var reg 32 - PCNext [31:0] $end
$upscope $end
$scope begin $ivl_for_loop0 $end
$var integer 32 . i [31:0] $end
$upscope $end
$upscope $end
$enddefinitions $end
$comment Show the parameter values. $end
$dumpall
$end
#0
$dumpvars
b0 .
b100 -
b0 ,
b100 +
bx *
b0 )
bx (
1'
bx &
b0 %
1$
bx #
b0 "
b100 !
$end
#5000
b1 .
0$
#10000
b1000 -
b1000 !
b1000 +
b100 "
b100 ,
b10 .
1$
0'
#15000
b11 .
0$
#20000
b1100 -
b1100 !
b1100 +
b1000 "
b1000 ,
b100 .
1$
#25000
b101 .
0$
#30000
b10000 -
b10000 !
b10000 +
b1100 "
b1100 ,
b110 .
1$
#35000
b111 .
0$
#40000
b10100 -
b10100 !
b10100 +
b10000 "
b10000 ,
b1000 .
1$
#45000
b1001 .
0$
#50000
b11000 -
b11000 !
b11000 +
b10100 "
b10100 ,
b1010 .
1$
#55000
b1011 .
0$
#60000
b1010100 !
b1010100 +
b1010000 "
b1010000 ,
b1010000 -
b1100 .
1$
b1 %
b1 )
b1010000 &
b1010000 *
#65000
b1101 .
0$
#70000
b1011000 !
b1011000 +
b1010100 "
b1010100 ,
b1011000 -
b1110 .
1$
b0 %
b0 )
#75000
b1111 .
0$
#80000
b1011100 -
b1011100 !
b1011100 +
b1011000 "
b1011000 ,
b10000 .
1$
#85000
b10001 .
0$
#90000
b1100000 -
b1100000 !
b1100000 +
b1011100 "
b1011100 ,
b10010 .
1$
#95000
b10011 .
0$
#100000
b100000100 !
b100000100 +
b100000000 "
b100000000 ,
b100000000 -
b10100 .
1$
b10 %
b10 )
b100000000 #
b100000000 (
#105000
b10101 .
0$
#110000
b100001000 !
b100001000 +
b100000100 "
b100000100 ,
b100001000 -
b10110 .
1$
b0 %
b0 )
#115000
b10111 .
0$
#120000
b100001100 -
b100001100 !
b100001100 +
b100001000 "
b100001000 ,
b11000 .
1$
#125000
b11001 .
0$
#130000
b100 -
b100 !
b100 +
b0 "
b0 ,
b11010 .
1$
1'
#135000
b11011 .
0$
#140000
b1000 -
b1000 !
b1000 +
b100 "
b100 ,
b11100 .
1$
0'
#145000
b11101 .
0$
#150000
b1100 -
b1100 !
b1100 +
b1000 "
b1000 ,
b11110 .
1$
