alu/alu.sv
module alu (output logic signed [31:0] ALUResult,
            output logic Zero, Negative,
            input logic signed [31:0] SrcA, SrcB,
            input logic [4:0] ALUControl);

logic carry_in;
logic zero_buffer, negative_buffer;
logic [1:0] ALUOp;
logic [31:0] shiftResult, sltResult, arithResult, logicResult;

// Extract Operation code for ALU multiplexer
assign ALUOp = ALUControl[1:0];

// Shfift Operations
assign shiftResult = (ALUControl[4]) ? SrcA >> SrcB[4:0] : SrcA << SrcB[4:0];

// SLT and Airthmetic operations
assign arithResult = (ALUControl[3]) ? SrcA - SrcB : SrcA + SrcB;
assign sltResult = (arithResult[31]) ? 32'd1 : 32'd0;

// Logic Operations
assign logicResult = (ALUControl[2]) ? (SrcA | SrcB) : (SrcA & SrcB);

// Zero and Negative
assign zero_buffer = (ALUResult == 32'd0) ? 1 : 0;
assign negative_buffer = (ALUResult[31]) ? 1 : 0;

always_comb
     begin
          case (ALUOp)
               2'b00: ALUResult = shiftResult;
               2'b01: ALUResult = sltResult;
               2'b10: ALUResult = arithResult;
               2'b11: ALUResult = logicResult;
               default: ALUResult = 32'd0;
          endcase

          Zero = zero_buffer;
          Negative = negative_buffer;
     end



endmodule

alu/alu_tb.sv
`timescale 1ns/1ps // Define Time Units
`include "alu.sv" // Include the module under test

module alu_tb;

// Declare test variables
logic signed [31:0] t_SrcA, t_SrcB, t_ALUResult;
logic [4:0] t_ALUControl;
logic t_Zero, t_Negative;

// Instantiate the module under test (DUT)
alu dut(
    .ALUResult(t_ALUResult),
    .Zero(t_Zero),
    .Negative(t_Negative),
    .SrcA(t_SrcA),
    .SrcB(t_SrcB),
    .ALUControl(t_ALUControl)
);

initial begin
    // Create a waveform dump file for GTKWave analysis
    $dumpfile("alu_tb.vcd"); 
    $dumpvars(0, alu_tb);
    
    // Test Vectors
    $display("Starting ALU Tests...");

    // Test Case 1: Left Shift (ALUControl[1:0]=00, ALUControl[4]=0)
    t_SrcA = 32'h000000F0;
    t_SrcB = 32'h00000004; // Shift left by 4 bits
    t_ALUControl = 5'b00000;
    #5;
    $display("Time = %3d, Left Shift: SrcA = %h, SrcB = %h, ALUControl = %b, ALUResult = %h, Zero = %b, Negative = %b", 
             $time, t_SrcA, t_SrcB, t_ALUControl, t_ALUResult, t_Zero, t_Negative);

    // Test Case 2: Right Shift (ALUControl[1:0]=00, ALUControl[4]=1)
    t_SrcA = 32'h0000000F;
    t_SrcB = 32'h00000004; // Shift Right by 4 bits
    t_ALUControl = 5'b10000;
    #5;
    $display("Time = %3d, Right Shift: SrcA = %h, SrcB = %h, ALUControl = %b, ALUResult = %h, Zero = %b, Negative = %b", 
             $time, t_SrcA, t_SrcB, t_ALUControl, t_ALUResult, t_Zero, t_Negative);

    // Test Case 3: SLT with SrcA < SrcB (ALUControl[1:0]=01)
    t_SrcA = 32'hFFFFFFFF; // -1 in 2's complement
    t_SrcB = 32'h00000001; // 1
    t_ALUControl = 5'b01001;
    #5;
    $display("Time = %3d, SLT (A<B): SrcA = %d, SrcB = %d, ALUControl = %b, ALUResult = %h, Zero = %b, Negative = %b", 
             $time, t_SrcA, t_SrcB, t_ALUControl, t_ALUResult, t_Zero, t_Negative);

    // Test Case 4: SLT with SrcA > SrcB (ALUControl[1:0]=01)
    t_SrcA = 32'h00000005; // 5
    t_SrcB = 32'h00000002; // 2
    t_ALUControl = 5'b01001;
    #5;
    $display("Time = %3d, SLT (A>B): SrcA = %d, SrcB = %d, ALUControl = %b, ALUResult = %h, Zero = %b, Negative = %b", 
             $time, t_SrcA, t_SrcB, t_ALUControl, t_ALUResult, t_Zero, t_Negative);

    // Test Case 5: Addition (ALUControl[1:0]=10, ALUControl[3]=0)
    t_SrcA = 32'h00000007; // 7
    t_SrcB = 32'h00000003; // 3
    t_ALUControl = 5'b00010;
    #5;
    $display("Time = %3d, Addition: SrcA = %d, SrcB = %d, ALUControl = %b, ALUResult = %d, Zero = %b, Negative = %b", 
             $time, t_SrcA, t_SrcB, t_ALUControl, t_ALUResult, t_Zero, t_Negative);

    // Test Case 6: Subtraction (ALUControl[1:0]=10, ALUControl[3]=1)
    t_SrcA = 32'h00000005; // 5
    t_SrcB = 32'h00000008; // 8
    t_ALUControl = 5'b01010;
    #5;
    $display("Time = %3d, Subtraction: SrcA = %d, SrcB = %d, ALUControl = %b, ALUResult = %d, Zero = %b, Negative = %b", 
             $time, t_SrcA, t_SrcB, t_ALUControl, t_ALUResult, t_Zero, t_Negative);

        // Test Case 6: Subtraction (ALUControl[1:0]=10, ALUControl[3]=1) where result is a negative value
    t_SrcA = 32'h00000008; // 5
    t_SrcB = 32'h00000005; // 8
    t_ALUControl = 5'b01010;
    #5;
    $display("Time = %3d, Subtraction: SrcA = %d, SrcB = %d, ALUControl = %b, ALUResult = %d, Zero = %b, Negative = %b", 
             $time, t_SrcA, t_SrcB, t_ALUControl, t_ALUResult, t_Zero, t_Negative);

    // Test Case 7: AND operation (ALUControl[1:0]=11, ALUControl[2]=0)
    t_SrcA = 32'hFF00FF00;
    t_SrcB = 32'h0F0F0F0F;
    t_ALUControl = 5'b00011;
    #5;
    $display("Time = %3d, AND: SrcA = %h, SrcB = %h, ALUControl = %b, ALUResult = %h, Zero = %b, Negative = %b", 
             $time, t_SrcA, t_SrcB, t_ALUControl, t_ALUResult, t_Zero, t_Negative);

    // Test Case 8: OR operation (ALUControl[1:0]=11, ALUControl[2]=1)
    t_SrcA = 32'hF0F0F0F0;
    t_SrcB = 32'h0F0F0FF0;
    t_ALUControl = 5'b00111;
    #5;
    $display("Time = %3d, OR: SrcA = %h, SrcB = %h, ALUControl = %b, ALUResult = %h, Zero = %b, Negative = %b", 
             $time, t_SrcA, t_SrcB, t_ALUControl, t_ALUResult, t_Zero, t_Negative);

    // Test Case 9: Zero flag test (subtract equal values)
    t_SrcA = 32'h00000010; // 16
    t_SrcB = 32'h00000010; // 16
    t_ALUControl = 5'b01010; // Subtraction
    #5;
    $display("Time = %3d, Zero Flag Test: SrcA = %d, SrcB = %d, ALUControl = %b, ALUResult = %d, Zero = %b, Negative = %b", 
             $time, t_SrcA, t_SrcB, t_ALUControl, t_ALUResult, t_Zero, t_Negative);

    $display("All tests completed.");
    #10;
    $finish;
end

// Monitor changes in signals
// initial begin
//     $monitor("Time = %3d, SrcA = %h, SrcB = %h, ALUControl = %b, ALUResult = %h, Zero = %b, Negative = %b",
//              $time, t_SrcA, t_SrcB, t_ALUControl, t_ALUResult, t_Zero, t_Negative);
// end

endmodule

alu_tb.vcd
$date
	Sat Mar 08 16:17:58 2025
$end
$version
	Icarus Verilog
$end
$timescale
	1ps
$end
$scope module alu_tb $end
$var wire 1 ! t_Zero $end
$var wire 1 " t_Negative $end
$var wire 32 # t_ALUResult [31:0] $end
$var reg 5 $ t_ALUControl [4:0] $end
$var reg 32 % t_SrcA [31:0] $end
$var reg 32 & t_SrcB [31:0] $end
$scope module dut $end
$var wire 5 ' ALUControl [4:0] $end
$var wire 32 ( SrcA [31:0] $end
$var wire 32 ) SrcB [31:0] $end
$var wire 1 * zero_buffer $end
$var wire 32 + sltResult [31:0] $end
$var wire 32 , shiftResult [31:0] $end
$var wire 1 - negative_buffer $end
$var wire 32 . logicResult [31:0] $end
$var wire 32 / arithResult [31:0] $end
$var wire 2 0 ALUOp [1:0] $end
$var reg 32 1 ALUResult [31:0] $end
$var reg 1 " Negative $end
$var reg 1 ! Zero $end
$upscope $end
$upscope $end
$enddefinitions $end
$comment Show the parameter values. $end
$dumpall
$end
#0
$dumpvars
b111100000000 1
b0 0
b11110100 /
b0 .
0-
b111100000000 ,
b0 +
0*
b100 )
b11110000 (
b0 '
b100 &
b11110000 %
b0 $
b111100000000 #
0"
0!
$end
#5000
1!
1*
b100 .
b0 #
b0 1
b0 ,
b10011 /
b10000 $
b10000 '
b1111 %
b1111 (
#10000
0!
0*
b1 #
b1 1
b1 +
b1 .
b1 0
b11111111111111111111111111111110 ,
b11111111111111111111111111111110 /
b1001 $
b1001 '
b1 &
b1 )
b11111111111111111111111111111111 %
b11111111111111111111111111111111 (
#15000
1!
1*
b0 #
b0 1
b0 +
b0 .
b10100 ,
b11 /
b10 &
b10 )
b101 %
b101 (
#20000
0!
0*
b11 .
b1010 #
b1010 1
b10 0
b111000 ,
b1010 /
b10 $
b10 '
b11 &
b11 )
b111 %
b111 (
#25000
1"
1-
b1 +
b0 .
b11111111111111111111111111111101 #
b11111111111111111111111111111101 1
b10100000000 ,
b11111111111111111111111111111101 /
b1010 $
b1010 '
b1000 &
b1000 )
b101 %
b101 (
#30000
0"
0-
b0 +
b11 #
b11 1
b100000000 ,
b11 /
b101 &
b101 )
b1000 %
b1000 (
#35000
0!
0*
b0 +
b1111000000000000111100000000 .
b1111000000000000111100000000 #
b1111000000000000111100000000 1
b11 0
b1111111100000000000000000000000 ,
b1110000100000000111000001111 /
b11 $
b11 '
b1111000011110000111100001111 &
b1111000011110000111100001111 )
b11111111000000001111111100000000 %
b11111111000000001111111100000000 (
#40000
1"
1-
b11111111111111111111111111110000 #
b11111111111111111111111111110000 1
b11111111111111111111111111110000 .
b11110000111100000000000000000000 ,
b11100000 /
b111 $
b111 '
b1111000011110000111111110000 &
b1111000011110000111111110000 )
b11110000111100001111000011110000 %
b11110000111100001111000011110000 (
#45000
0"
1!
1*
0-
b10000 .
b0 #
b0 1
b10 0
b100000000000000000000 ,
b0 /
b1010 $
b1010 '
b10000 &
b10000 )
b10000 %
b10000 (
