data_memory_and_io.sv
module data_memory_and_io (output logic [31:0] RD, CPUOut,
                            input logic [31:0] A, WD, CPUIn,
                            input logic WE, CLK);
 
logic [7:0] DM [0:1023];

// RDsel seclect whether to read from CPUIn or memory
// Write Enable for CPUout is WEOut
// Write Enable for Memory is WEM
logic RDsel, WEM, WEOut;

assign RDsel = (A == 32'h7FFFFFFC) ? 1 : 0; 

assign RD = (RDsel) ? CPUIn : {DM[A+3], DM[A+2], DM[A+1], DM[A]};

always_comb
begin
   if ((WE) & (A == 32'h7FFFFFFC)) begin
        WEOut = 1;
        WEM = 0;
    end
    else if ((WE) & (A != 32'h7FFFFFFC)) begin
        WEOut = 0;
        WEM = 1;
    end
    else begin
        WEOut = 0;
        WEM = 0;
    end        
end

always_ff @ (posedge CLK)
begin
    if (WEM)  {DM [A+3], DM [A+2], DM [A+1], DM [A]} <= WD;
    if (WEOut) CPUOut <= WD;
end

endmodule

alu/alu.sv
module alu (output logic signed [31:0] ALUResult,
            output logic Zero, Negative,
            input logic signed [31:0] SrcA, SrcB,
            input logic [4:0] ALUControl);

logic carry_in;
logic zero_buffer, negative_buffer;
logic [1:0] ALUOp;
logic [31:0] shiftResult, sltResult, arithResult, logicResult;

// Extract Operation code for ALU multiplexer
assign ALUOp = ALUControl[1:0];

// Shfift Operations
assign shiftResult = (ALUControl[4]) ? SrcA >> SrcB[4:0] : SrcA << SrcB[4:0];

// SLT and Airthmetic operations
assign arithResult = (ALUControl[3]) ? SrcA - SrcB : SrcA + SrcB;
assign sltResult = (arithResult[31]) ? 32'd1 : 32'd0;

// Logic Operations
assign logicResult = (ALUControl[2]) ? (SrcA | SrcB) : (SrcA & SrcB);

// Zero and Negative
assign zero_buffer = (ALUResult == 32'd0) ? 1 : 0;
assign negative_buffer = (ALUResult[31]) ? 1 : 0;

always_comb
     begin
          case (ALUOp)
               2'b00: ALUResult = shiftResult;
               2'b01: ALUResult = sltResult;
               2'b10: ALUResult = arithResult;
               2'b11: ALUResult = logicResult;
               default: ALUResult = 32'd0;
          endcase

          Zero = zero_buffer;
          Negative = negative_buffer;
     end



endmodule

reg_file.sv
module reg_file   (output logic [31:0] RD1, RD2,
                    input logic [31:0] WD3,
                    input logic [4:0] A1, A2, A3,
                    input logic WE3, CLK);

logic [31:0] RF [0:31];
 
assign RD1 = (A1==5'b0) ? 32'b0 : RF[A1];
assign RD2 = (A2==5'b0) ? 32'b0 : RF[A2];

always_ff @ (posedge CLK)
if (WE3) RF[A3] <= WD3;

endmodule

extend.sv
module extend (output logic [31:0] ImmExt,
                input logic [31:0] Instr,
                input logic [2:0] ImmSrc);

logic [31:0] imm_i, imm_s, imm_b, imm_u, imm_j;

assign imm_i = {{20{Instr[31]}}, Instr[31:20]};
assign imm_s = {{20{Instr[31]}}, Instr[31:25], Instr[11:7]};
assign imm_b = {{19{Instr[31]}}, Instr[31], Instr[7], Instr[30:25], Instr[11:8], 1'b0};
assign imm_u = {Instr[31:12], 12'b0};
assign imm_j = {{12{Instr[31]}}, Instr[19:12], Instr[20], Instr[30:21], 1'b0};

always_comb begin
    case (ImmSrc)
        3'b000: ImmExt = imm_i;
        3'b001: ImmExt = imm_s;
        3'b010: ImmExt = imm_b;
        3'b011: ImmExt = imm_u;
        3'b100: ImmExt = imm_j;
        default: ImmExt = 32'b0;
    endcase
end

endmodule

task 1/control_unit/control_unit.sv
module control_unit (output logic [1:0] PCSrc, 
                     output logic [1:0] ResultSrc,
                     output logic MemWrite, ALUSrc, RegWrite,
                     output logic [4:0] ALUControl,
                     output logic [2:0] ImmSrc,
                     input logic [31:0] Instr,
                     input logic Zero, Negative);

    logic [6:0] opcode;
    logic [2:0] funct3;
    logic [6:0] funct7;
    
    assign opcode = Instr[6:0];     // Extract opcode
    assign funct3 = Instr[14:12];   // Extract funct3 field
    assign funct7 = Instr[31:25];   // Extract funct7 field

    always_comb begin
        // Default values
        PCSrc = 2'b00;
        ResultSrc = 2'b00;
        MemWrite = 0;
        ALUSrc = 0;
        RegWrite = 1;
        ALUControl = 5'b00000;
        ImmSrc = 3'b000;

        // Additional control signals based on instruction type
        case (opcode)
            7'b0110011: begin // R-type
                RegWrite = 1;
                ALUSrc = 0;
                MemWrite = 0;
                ResultSrc = 2'b01;
                PCSrc = 2'b00;
                ImmSrc = 3'b000;

                // Deciding the operations for the R-type instructions
                case (funct3)
                    3'b000: begin
                        case (funct7)
                            7'b0000000: ALUControl = 5'b00010; // add
                            7'b0100000: ALUControl = 5'b01010; // sub
                            default: ALUControl = 5'b00000;
                        endcase
                    end
                    3'b001: ALUControl = 5'b00000; // sll
                    3'b010: ALUControl = 5'b01001; // slt
                    3'b101: ALUControl = 5'b10000; // srl
                    3'b110: ALUControl = 5'b00111; // or
                    3'b111: ALUControl = 5'b00011; // and
                    default: ALUControl = 5'b00000;
                endcase
            end
        

            7'b0010011: begin // I-type
                RegWrite = 1;
                ALUSrc = 1;
                ImmSrc = 3'b000;
                MemWrite = 0;
                ResultSrc = 2'b01;
                PCSrc = 2'b00;
                
                case (funct3)
                    3'd0: ALUControl = 5'b00010; // addi
                    3'd1: ALUControl = 5'b00000; // slli
                    3'd2: ALUControl = 5'b01001; // slti
                    3'd5: ALUControl = 5'b10000; // srli
                    3'd6: ALUControl = 5'b00111; // ori
                    3'd7: ALUControl = 5'b00011; // andi
                    default: ALUControl = 5'b00000;
                endcase
            end

            7'b0000011: begin // lw
                RegWrite = 1;
                ALUSrc = 1;
                ImmSrc = 3'b000;
                MemWrite = 0;
                ResultSrc = 2'b10;
                ALUControl = 5'b00010; // Add for address calculation
                PCSrc = 2'b00;
            end

            7'b0100011: begin // sw
                RegWrite = 0;
                ALUSrc = 1;
                ImmSrc = 3'b001;
                MemWrite = 1;
                ALUControl = 5'b00010; // Add for address calculation
                PCSrc = 2'b00;
            end

            7'b1100011: begin // B-type
                RegWrite = 0;
                ALUSrc = 0;
                ImmSrc = 3'b010;
                MemWrite = 0;
                ResultSrc = 2'b00;

                case (funct3)
                    3'd0: begin // beq
                        PCSrc = Zero ? 2'b01 : 2'b00;
                        ALUControl = 5'b01010;;
                    end

                    3'd1: begin // bne
                        PCSrc = !Zero ? 2'b01 : 2'b00;
                        ALUControl = 5'b01010;
                    end

                    3'd4: begin
                        PCSrc = Negative ? 2'b01 : 2'b00; // blt
                        ALUControl = 5'b01001;
                    end

                    3'd5: begin
                        PCSrc = !Negative ? 2'b01 : 2'b00; // bge
                        ALUControl = 5'b01001;
                    end
                
                    default: PCSrc = 2'b00;
                endcase
            end


            7'b1101111: begin // jal
                RegWrite = 1;
                ALUSrc = 0;
                ImmSrc = 3'b100;
                MemWrite = 0;
                ResultSrc = 2'b11;
                PCSrc = 2'b01;
                ALUControl = 5'b00000; // Add for address calculation
            end


            7'b1100111: begin // jalr
                RegWrite = 1;
                ImmSrc = 3'b000;
                ALUSrc = 1;
                ALUControl = 5'b00010;
                PCSrc = 2'b10;
                ResultSrc = 2'b11; // Write PC+4 to register
                MemWrite = 0;
            end


            7'b0110111: begin // lui
                RegWrite = 1;
                ALUSrc = 0;
                ImmSrc = 3'b011;
                ResultSrc = 2'b00;
                MemWrite = 0;
                ALUControl = 5'b00000;
                PCSrc = 2'b00;
            end


            default: begin
                PCSrc = 2'b00;
                ResultSrc = 2'b00;
                MemWrite = 0;
                ALUSrc = 0;
                RegWrite = 0;
                ALUControl = 5'b00000;
                ImmSrc = 3'b000;
            end
        endcase
    end

endmodule

task 1/instruction_memory.sv
module instruction_memory (output logic [31:0] Instr,
                            input logic [31:0] PC);

logic [7:0] IM [0:255];
logic [31:0] prog [0:63];
logic [31:0] PC_divided_by_4;
 
initial
// $readmemh ("program.txt", prog);
$readmemh ("instruction_txt/task2_2_program.txt", prog);

assign Instr = prog[PC_divided_by_4];

assign PC_divided_by_4 = PC/4;

endmodule

program_counter.sv
module program_counter (output logic [31:0] PC, PCPlus4,
                        input logic [31:0] PCTarget, ALUResult,
                        input logic [1:0] PCSrc, 
                        input logic Reset, CLK);

logic [31:0] PCNext;

always_comb begin
    case (PCSrc)
        2'b00: PCNext = PC + 4;
        2'b01: PCNext = PCTarget;
        2'b10: PCNext = ALUResult;
        default: PCNext = 32'd0;
    endcase
end

always_ff @ (posedge CLK) begin
    if (Reset) PC <= 32'd0;
    else PC <= PCNext;
end

endmodule

risc_v.sv
`include "instruction_memory.sv"
`include "reg_file.sv"
`include "extend/extend.sv"
`include "alu/alu.sv"
`include "data_memory_and_io.sv"
`include "program_counter/program_counter.sv"
`include "control_unit/control_unit.sv"

module risc_v(
    output logic [31:0] CPUOut,    // Data written out (if address == 0x7FFFFFFC)
    input  logic [31:0] CPUIn,     // Data read in  (if address == 0x7FFFFFFC)
    input  logic Reset, CLK
    );

    logic [31:0] Instr, WD3, RD1, RD2, SrcA, SrcB, ALUResult, RD, Result, ImmExt, PCTarget, PC, PCPlus4;
    logic [4:0]  A1, A2, A3;
    logic        MemWrite, ALUSrc, RegWrite;
    logic        Zero, Negative;
    logic [4:0]  ALUControl;
    logic [2:0]  ImmSrc;
    logic [1:0]  ResultSrc;
    logic [1:0]  PCSrc;

    // logic [31:0] WD, PCNext,     // WD PCNext


    //--------------------------------------------------------
    // 1) Program Counter
    //--------------------------------------------------------
    program_counter new_program_counter (
        .PC      (PC),
        .PCPlus4 (PCPlus4),
        .PCTarget(PCTarget),
        .ALUResult(ALUResult),
        .PCSrc   (PCSrc),
        .Reset   (Reset),
        .CLK     (CLK)
    );
    
    //--------------------------------------------------------
    // 2) Instruction Memory
    //--------------------------------------------------------
    instruction_memory new_instruction_memory (
        .Instr (Instr),
        .PC    (PC)
    );

    //--------------------------------------------------------
    // 3) Control Unit
    //--------------------------------------------------------
    control_unit new_control_unit (
        .PCSrc      (PCSrc),
        .ResultSrc  (ResultSrc),
        .MemWrite   (MemWrite),
        .ALUSrc     (ALUSrc),
        .RegWrite   (RegWrite),
        .ALUControl (ALUControl),
        .ImmSrc     (ImmSrc),
        .Instr      (Instr),
        .Zero       (Zero),
        .Negative   (Negative)
    );

    //--------------------------------------------------------
    // 4) Immediate Extension
    //--------------------------------------------------------
    extend new_extend (
        .ImmExt (ImmExt),
        .Instr  (Instr),
        .ImmSrc (ImmSrc)
    );

    //--------------------------------------------------------
    // 5) Register File
    //--------------------------------------------------------

    // Assign the register file inputs
    assign A1 = Instr[19:15];  // rs1
    assign A2 = Instr[24:20];  // rs2
    assign A3 = Instr[11:7];   // rd

    reg_file new_reg_file (
        .RD1  (RD1),
        .RD2  (RD2),
        .WD3  (WD3),               // Write-back data
        .A1   (A1),      // rs1
        .A2   (A2),      // rs2
        .A3   (A3),       // rd
        .WE3  (RegWrite),
        .CLK  (CLK)
    );

    //--------------------------------------------------------
    // 6) ALU
    //--------------------------------------------------------
    // ALU SrcA is always RD1
    assign SrcA = RD1;
    // ALU SrcB is either RD2 or the sign-extended immediate
    assign SrcB = (ALUSrc) ? ImmExt : RD2;

    alu new_alu (
        .ALUResult (ALUResult),
        .Zero      (Zero),
        .Negative  (Negative),
        .SrcA      (SrcA),
        .SrcB      (SrcB),
        .ALUControl(ALUControl)
    );

    //--------------------------------------------------------
    // 7) Data Memory + I/O
    //--------------------------------------------------------
    data_memory_and_io new_data_memory_and_io (
        .RD     (RD),
        .CPUOut (CPUOut),
        .A      (ALUResult),
        .WD     (RD2),        // Data to store comes from register file
        .CPUIn  (CPUIn),
        .WE     (MemWrite),
        .CLK    (CLK)
    );

    //--------------------------------------------------------
    // 8) Branch Target Adder
    //--------------------------------------------------------
    assign PCTarget = PC + ImmExt;  // For branches & jal

    //--------------------------------------------------------
    // 9) Result Mux (Write-back to Register File)
    //    ResultSrc chooses among:
    //      2'b00 -> ImmExt     (for LUI)
    //      2'b01 -> ALUResult  (R-type, I-type)
    //      2'b10 -> RD         (LW)
    //      2'b11 -> PCPlus4    (JAL, JALR)
    //--------------------------------------------------------

    always_comb begin
        case (ResultSrc)
            2'b00:  Result = ImmExt;     // LUI
            2'b01:  Result = ALUResult;  // R-type / I-type
            2'b10:  Result = RD;         // LW
            2'b11:  Result = PCPlus4;    // JAL, JALR
            default:Result = 32'd0;
        endcase
    end

    assign WD3 = Result; // Connect mux output to register file
endmodule

task 1/risc_v_tb.sv
`timescale 1ns/1ps
`include "risc_v.sv"

module risc_v_tb;
  // Declare signals
  logic [31:0] CPUOut, CPUIn;
  logic Reset, CLK;
  
  // Instantiate the DUT
  risc_v dut(CPUOut, CPUIn, Reset, CLK);
  
  // Generate clock signal with 20 ns period
  initial begin
    CLK = 0;
    forever #5 CLK = ~CLK;
  end
  
  // Apply stimulus and generate dump file for GTKWave
  initial begin
    // Dump file and variables for GTKWave
    $dumpfile("risc_v_tb.vcd");
    $dumpvars(0, risc_v_tb);
    
    // Initialize inputs
    Reset = 1;
    CPUIn = 32'h0000001f;  // Default value; adjust as necessary
    
    // Hold reset for 20 ns, then release
    #10;
    Reset = 0;
    
    // Let simulation run for additional time to observe behavior
    #1500;
    
    $finish;  // End simulation
  end


  // Display selected signals at every negative clock edge
  always @(negedge CLK)
    $display("t = %3d, CPUIn = %d, CPUOut = %d, Reset = %b, PCSrc = %b, PC = %d, PCTarget = %h, ImmExt = %h, Instr = %h, ALUResult = %d", 
             $time, CPUIn, CPUOut, Reset, dut.PCSrc, dut.PC, dut.PCTarget, dut.ImmExt, dut.Instr, dut.ALUResult);

endmodule

task 1/risc_v_tb.vcd
$date
	Tue Mar 11 02:05:19 2025
$end
$version
	Icarus Verilog
$end
$timescale
	1ps
$end
$scope module risc_v_tb $end
$var wire 32 ! CPUOut [31:0] $end
$var reg 1 " CLK $end
$var reg 32 # CPUIn [31:0] $end
$var reg 1 $ Reset $end
$scope module dut $end
$var wire 1 " CLK $end
$var wire 32 % CPUIn [31:0] $end
$var wire 1 $ Reset $end
$var wire 32 & SrcA [31:0] $end
$var wire 32 ' WD3 [31:0] $end
$var wire 1 ( Zero $end
$var wire 32 ) SrcB [31:0] $end
$var wire 2 * ResultSrc [1:0] $end
$var wire 1 + RegWrite $end
$var wire 32 , RD2 [31:0] $end
$var wire 32 - RD1 [31:0] $end
$var wire 32 . RD [31:0] $end
$var wire 32 / PCTarget [31:0] $end
$var wire 2 0 PCSrc [1:0] $end
$var wire 32 1 PCPlus4 [31:0] $end
$var wire 32 2 PC [31:0] $end
$var wire 1 3 Negative $end
$var wire 1 4 MemWrite $end
$var wire 32 5 Instr [31:0] $end
$var wire 3 6 ImmSrc [2:0] $end
$var wire 32 7 ImmExt [31:0] $end
$var wire 32 8 CPUOut [31:0] $end
$var wire 1 9 ALUSrc $end
$var wire 32 : ALUResult [31:0] $end
$var wire 5 ; ALUControl [4:0] $end
$var wire 5 < A3 [4:0] $end
$var wire 5 = A2 [4:0] $end
$var wire 5 > A1 [4:0] $end
$var reg 32 ? Result [31:0] $end
$scope module new_alu $end
$var wire 32 @ SrcA [31:0] $end
$var wire 32 A SrcB [31:0] $end
$var wire 1 B zero_buffer $end
$var wire 32 C sltResult [31:0] $end
$var wire 32 D shiftResult [31:0] $end
$var wire 1 E negative_buffer $end
$var wire 32 F logicResult [31:0] $end
$var wire 32 G arithResult [31:0] $end
$var wire 2 H ALUOp [1:0] $end
$var wire 5 I ALUControl [4:0] $end
$var reg 32 J ALUResult [31:0] $end
$var reg 1 3 Negative $end
$var reg 1 ( Zero $end
$upscope $end
$scope module new_control_unit $end
$var wire 1 3 Negative $end
$var wire 1 ( Zero $end
$var wire 7 K opcode [6:0] $end
$var wire 7 L funct7 [6:0] $end
$var wire 3 M funct3 [2:0] $end
$var wire 32 N Instr [31:0] $end
$var reg 5 O ALUControl [4:0] $end
$var reg 1 9 ALUSrc $end
$var reg 3 P ImmSrc [2:0] $end
$var reg 1 4 MemWrite $end
$var reg 2 Q PCSrc [1:0] $end
$var reg 1 + RegWrite $end
$var reg 2 R ResultSrc [1:0] $end
$upscope $end
$scope module new_data_memory_and_io $end
$var wire 32 S A [31:0] $end
$var wire 1 " CLK $end
$var wire 32 T CPUIn [31:0] $end
$var wire 1 4 WE $end
$var wire 32 U WD [31:0] $end
$var wire 1 V RDsel $end
$var wire 32 W RD [31:0] $end
$var reg 32 X CPUOut [31:0] $end
$var reg 1 Y WEM $end
$var reg 1 Z WEOut $end
$upscope $end
$scope module new_extend $end
$var wire 3 [ ImmSrc [2:0] $end
$var wire 32 \ imm_u [31:0] $end
$var wire 32 ] imm_s [31:0] $end
$var wire 32 ^ imm_j [31:0] $end
$var wire 32 _ imm_i [31:0] $end
$var wire 32 ` imm_b [31:0] $end
$var wire 32 a Instr [31:0] $end
$var reg 32 b ImmExt [31:0] $end
$upscope $end
$scope module new_instruction_memory $end
$var wire 32 c Instr [31:0] $end
$var wire 32 d PC_divided_by_4 [31:0] $end
$var wire 32 e PC [31:0] $end
$upscope $end
$scope module new_program_counter $end
$var wire 32 f ALUResult [31:0] $end
$var wire 1 " CLK $end
$var wire 2 g PCSrc [1:0] $end
$var wire 32 h PCTarget [31:0] $end
$var wire 1 $ Reset $end
$var wire 32 i PCPlus4 [31:0] $end
$var reg 32 j PC [31:0] $end
$var reg 32 k PCNext [31:0] $end
$upscope $end
$scope module new_reg_file $end
$var wire 5 l A1 [4:0] $end
$var wire 5 m A2 [4:0] $end
$var wire 5 n A3 [4:0] $end
$var wire 1 " CLK $end
$var wire 32 o WD3 [31:0] $end
$var wire 1 + WE3 $end
$var wire 32 p RD2 [31:0] $end
$var wire 32 q RD1 [31:0] $end
$upscope $end
$upscope $end
$upscope $end
$enddefinitions $end
$comment Show the parameter values. $end
$dumpall
$end
#0
$dumpvars
bx q
bx p
bx o
bx n
bx m
bx l
bx k
bx j
bx i
bx h
b0 g
bx f
bx e
bx d
bx c
bx b
bx a
bx0 `
bx _
bx0 ^
bx ]
bx000000000000 \
b0 [
0Z
0Y
bx X
bx W
xV
bx U
b11111 T
bx S
b0 R
b0 Q
b0 P
b0 O
bx N
bx M
bx L
bx K
bx J
b0 I
b0 H
bx G
bx F
xE
bx D
b0x C
xB
bx A
bx @
bx ?
bx >
bx =
bx <
b0 ;
bx :
09
bx 8
bx 7
b0 6
bx 5
04
x3
bx 2
bx 1
b0 0
bx /
bx .
bx -
bx ,
0+
b0 *
bx )
x(
bx '
bx &
b11111 %
1$
b11111 #
0"
bx !
$end
#5000
03
1(
0E
1B
0V
b0 :
b0 J
b0 S
b0 f
b0 C
b0 D
b0 G
b0 F
b10000000000000000000000000000000 '
b10000000000000000000000000000000 o
b10000000000000000000000000000000 ?
b0 )
b0 A
b10000000000000000000000000000000 /
b10000000000000000000000000000000 h
b10000000000000000000000000000000 7
b10000000000000000000000000000000 b
b11 6
b11 P
b11 [
1+
b0 ,
b0 U
b0 p
b0 &
b0 @
b0 -
b0 q
b100 k
b11111111111100000000000000000000 ^
b10000000000000000000000000000000 \
b11111111111111111111000000011110 `
b11111111111111111111100000011110 ]
b11111111111111111111100000000000 _
b1000000 L
b0 M
b110111 K
b11110 <
b11110 n
b0 =
b0 m
b0 >
b0 l
b100 1
b100 i
b10000000000000000000111100110111 5
b10000000000000000000111100110111 N
b10000000000000000000111100110111 a
b10000000000000000000111100110111 c
b0 d
b0 2
b0 e
b0 j
1"
#10000
0"
0$
#15000
b11111 .
b11111 W
03
1V
0E
0(
0B
b10000000000000000000000000000000 F
b0 C
b1111111111111111111111111111100 :
b1111111111111111111111111111100 J
b1111111111111111111111111111100 S
b1111111111111111111111111111100 f
b10 H
b1111111111111111111111111111100 '
b1111111111111111111111111111100 o
b1111111111111111111111111111100 ?
b11111111111111111111111111111100 )
b11111111111111111111111111111100 A
b0 D
b1111111111111111111111111111100 G
b11111111111111111111111111111100 7
b11111111111111111111111111111100 b
b10 ;
b10 I
b10 O
b1 *
b1 R
19
b0 6
b0 P
b0 [
bx ,
bx U
bx p
b10000000000000000000000000000000 &
b10000000000000000000000000000000 @
b10000000000000000000000000000000 -
b10000000000000000000000000000000 q
b11111111111111110000011111111100 ^
b11111111110011110000000000000000 \
b11111111111111111111011111111110 `
b11111111111111111111111111111110 ]
b11111111111111111111111111111100 _
b1111111 L
b10011 K
b11100 =
b11100 m
b11110 >
b11110 l
b1000 k
b1000 1
b1000 i
b11111111110011110000111100010011 5
b11111111110011110000111100010011 N
b11111111110011110000111100010011 a
b11111111110011110000111100010011 c
b1 d
b0 /
b0 h
b100 2
b100 e
b100 j
1"
#20000
0"
#25000
03
1(
1B
0E
bx .
bx W
b0 C
0V
b0 )
b0 A
b0 '
b0 o
b0 ?
b0 F
b0 :
b0 J
b0 S
b0 f
b0 7
b0 b
b10 ;
b10 I
b10 O
09
b1 *
b1 R
b0 ,
b0 U
b0 p
b0 D
b0 G
b0 ^
b0 \
b110 `
b110 ]
b0 _
b0 L
b110011 K
b110 <
b110 n
b0 =
b0 m
b0 >
b0 l
b1100 k
b0 &
b0 @
b0 -
b0 q
b1100 1
b1100 i
b1100110011 5
b1100110011 N
b1100110011 a
b1100110011 c
b10 d
b1000 /
b1000 h
b1000 2
b1000 e
b1000 j
1"
#30000
0"
#35000
b100000000110 `
b111 ]
b111 <
b111 n
b10000 k
b10000 1
b10000 i
b1110110011 5
b1110110011 N
b1110110011 a
b1110110011 c
b11 d
b1100 /
b1100 h
b1100 2
b1100 e
b1100 j
1"
#40000
0"
#45000
19
b10 ;
b10 I
b10 O
b1 *
b1 R
b11100 `
b11100 ]
b10011 K
b11100 <
b11100 n
b10100 k
b10100 1
b10100 i
b111000010011 5
b111000010011 N
b111000010011 a
b111000010011 c
b100 d
b10000 /
b10000 h
b10000 2
b10000 e
b10000 j
1"
#50000
0"
#55000
b10 ;
b10 I
b10 O
19
b1 *
b1 R
0(
0B
b1000 '
b1000 o
b1000 ?
b1000 :
b1000 J
b1000 S
b1000 f
b1000 G
b1000 )
b1000 A
b1000 7
b1000 b
bx ,
bx U
bx p
b1000 ^
b100000000000000000000000 \
b100000011100 `
b11101 ]
b1000 _
b11101 <
b11101 n
b1000 =
b1000 m
b11000 k
b11000 1
b11000 i
b100000000000111010010011 5
b100000000000111010010011 N
b100000000000111010010011 a
b100000000000111010010011 c
b101 d
b11100 /
b11100 h
b10100 2
b10100 e
b10100 j
1"
#60000
0"
#65000
b11 '
b11 o
b11 ?
b11 :
b11 J
b11 S
b11 f
b11 G
b11 )
b11 A
b11 7
b11 b
b100000000010 ^
b1100000000000000000000 \
b1000 `
b1000 ]
b11 _
b1000 <
b1000 n
b11 =
b11 m
b11100 k
b11100 1
b11100 i
b1100000000010000010011 5
b1100000000010000010011 N
b1100000000010000010011 a
b1100000000010000010011 c
b110 d
b11011 /
b11011 h
b11000 2
b11000 e
b11000 j
1"
#70000
0"
#75000
b100 '
b100 o
b100 ?
b100 :
b100 J
b100 S
b100 f
b100 G
b100 )
b100 A
b100 7
b100 b
b100 ^
b10000000000000000000000 \
b100000001000 `
b1001 ]
b100 _
b1001 <
b1001 n
b100 =
b100 m
b100000 k
b100000 1
b100000 i
b10000000000010010010011 5
b10000000000010010010011 N
b10000000000010010010011 a
b10000000000010010010011 c
b111 d
b100000 /
b100000 h
b11100 2
b11100 e
b11100 j
1"
#80000
0"
#85000
1(
1B
b0 '
b0 o
b0 ?
b0 F
b0 :
b0 J
b0 S
b0 f
b11 H
b1 )
b1 A
b1000 D
b101 G
b1 7
b1 b
b11 ;
b11 I
b11 O
19
b1 *
b1 R
b100 &
b100 @
b100 -
b100 q
b1001111100000000000 ^
b101001111000000000000 \
b11100 `
b11100 ]
b1 _
b111 M
b11100 <
b11100 n
b1 =
b1 m
b1001 >
b1001 l
b100100 k
b100100 1
b100100 i
b101001111111000010011 5
b101001111111000010011 N
b101001111111000010011 a
b101001111111000010011 c
b1000 d
b100001 /
b100001 h
b100000 2
b100000 e
b100000 j
1"
#90000
0"
#95000
1(
1B
b0 :
b0 J
b0 S
b0 f
b10 H
b0 )
b0 A
b1000 '
b1000 o
b1000 ?
b0 D
b0 G
b1000 7
b1000 b
b1 0
b1 Q
b1 g
b10 6
b10 P
b10 [
0+
b1010 ;
b1010 I
b1010 O
09
b0 *
b0 R
b0 ,
b0 U
b0 p
b0 &
b0 @
b0 -
b0 q
b11100000000000000000 ^
b11100000000000000000 \
b1000 `
b1000 ]
b0 _
b0 M
b1100011 K
b1000 <
b1000 n
b0 =
b0 m
b11100 >
b11100 l
b101100 k
b101000 1
b101000 i
b11100000010001100011 5
b11100000010001100011 N
b11100000010001100011 a
b11100000010001100011 c
b1001 d
b101100 /
b101100 h
b100100 2
b100100 e
b100100 j
1"
#100000
0"
#105000
0(
0B
b1 F
b110 :
b110 J
b110 S
b110 f
b110 '
b110 o
b110 ?
b0 H
b1 )
b1 A
b110 D
b100 G
b1 7
b1 b
b1 *
b1 R
19
b0 6
b0 P
b0 [
b0 ;
b0 I
b0 O
1+
b0 0
b0 Q
b0 g
bx ,
bx U
bx p
b11 &
b11 @
b11 -
b11 q
b1000001100000000000 ^
b101000001000000000000 \
b1 _
b1 M
b10011 K
b1 =
b1 m
b1000 >
b1000 l
b110000 k
b110000 1
b110000 i
b101000001010000010011 5
b101000001010000010011 N
b101000001010000010011 a
b101000001010000010011 c
b1011 d
b101101 /
b101101 h
b101100 2
b101100 e
b101100 j
1"
#110000
0"
#115000
b10 '
b10 o
b10 ?
b0 F
b10 :
b10 J
b10 S
b10 f
b10 D
b101 G
b10000 ;
b10000 I
b10000 O
19
b1 *
b1 R
b100 &
b100 @
b100 -
b100 q
b1001101100000000000 ^
b101001101000000000000 \
b100000001000 `
b1001 ]
b101 M
b1001 <
b1001 n
b1001 >
b1001 l
b110100 k
b110100 1
b110100 i
b101001101010010010011 5
b101001101010010010011 N
b101001101010010010011 a
b101001101010010010011 c
b1100 d
b110001 /
b110001 h
b110000 2
b110000 e
b110000 j
1"
#120000
0"
#125000
b10 H
b1 '
b1 o
b1 ?
b1 :
b1 J
b1 S
b1 f
b10 ;
b10 I
b10 O
19
b1 *
b1 R
b0 D
b1 G
b111000100000000000 ^
b100111000000000000000 \
b100000000110 `
b111 ]
b0 M
b111 <
b111 n
b111 >
b111 l
b111000 k
b0 &
b0 @
b0 -
b0 q
b111000 1
b111000 i
b100111000001110010011 5
b100111000001110010011 N
b100111000001110010011 a
b100111000001110010011 c
b1101 d
b110101 /
b110101 h
b110100 2
b110100 e
b110100 j
1"
#130000
0"
#135000
13
1E
b1 C
b0 F
b11111111111111111111111111111001 :
b11111111111111111111111111111001 J
b11111111111111111111111111111001 S
b11111111111111111111111111111001 f
b1000 )
b1000 A
b11111111111111111111111111101000 '
b11111111111111111111111111101000 o
b11111111111111111111111111101000 ?
b100000000 D
b11111111111111111111111111111001 G
b11111111111111111111111111101000 7
b11111111111111111111111111101000 b
b1 0
b1 Q
b1 g
b10 6
b10 P
b10 [
0+
b1010 ;
b1010 I
b1010 O
09
b0 *
b0 R
b1000 ,
b1000 U
b1000 p
b1 &
b1 @
b1 -
b1 q
b11111111111100111001111111111100 ^
b11111111110100111001000000000000 \
b11111111111111111111111111101000 `
b11111111111111111111111111101001 ]
b11111111111111111111111111111101 _
b1111111 L
b1 M
b1100011 K
b1001 <
b1001 n
b11101 =
b11101 m
b100000 k
b111100 1
b111100 i
b11111111110100111001010011100011 5
b11111111110100111001010011100011 N
b11111111110100111001010011100011 a
b11111111110100111001010011100011 c
b1110 d
b100000 /
b100000 h
b111000 2
b111000 e
b111000 j
1"
#140000
0"
#145000
03
0E
1(
b0 C
1B
b0 :
b0 J
b0 S
b0 f
b0 '
b0 o
b0 ?
b11 H
b1 )
b1 A
b100 D
b11 G
b1 7
b1 b
b1 *
b1 R
19
b0 6
b0 P
b0 [
b11 ;
b11 I
b11 O
1+
b0 0
b0 Q
b0 g
bx ,
bx U
bx p
b10 &
b10 @
b10 -
b10 q
b1001111100000000000 ^
b101001111000000000000 \
b11100 `
b11100 ]
b1 _
b0 L
b111 M
b10011 K
b11100 <
b11100 n
b1 =
b1 m
b1001 >
b1001 l
b100100 k
b100100 1
b100100 i
b101001111111000010011 5
b101001111111000010011 N
b101001111111000010011 a
b101001111111000010011 c
b1000 d
b100001 /
b100001 h
b100000 2
b100000 e
b100000 j
1"
#150000
0"
#155000
1(
1B
b0 :
b0 J
b0 S
b0 f
b10 H
b0 )
b0 A
b1000 '
b1000 o
b1000 ?
b0 D
b0 G
b1000 7
b1000 b
b1 0
b1 Q
b1 g
b10 6
b10 P
b10 [
0+
b1010 ;
b1010 I
b1010 O
09
b0 *
b0 R
b0 ,
b0 U
b0 p
b0 &
b0 @
b0 -
b0 q
b11100000000000000000 ^
b11100000000000000000 \
b1000 `
b1000 ]
b0 _
b0 M
b1100011 K
b1000 <
b1000 n
b0 =
b0 m
b11100 >
b11100 l
b101100 k
b101000 1
b101000 i
b11100000010001100011 5
b11100000010001100011 N
b11100000010001100011 a
b11100000010001100011 c
b1001 d
b101100 /
b101100 h
b100100 2
b100100 e
b100100 j
1"
#160000
0"
#165000
0(
0B
b1100 :
b1100 J
b1100 S
b1100 f
b1100 '
b1100 o
b1100 ?
b0 H
b1 )
b1 A
b1100 D
b111 G
b1 7
b1 b
b1 *
b1 R
19
b0 6
b0 P
b0 [
b0 ;
b0 I
b0 O
1+
b0 0
b0 Q
b0 g
bx ,
bx U
bx p
b110 &
b110 @
b110 -
b110 q
b1000001100000000000 ^
b101000001000000000000 \
b1 _
b1 M
b10011 K
b1 =
b1 m
b1000 >
b1000 l
b110000 k
b110000 1
b110000 i
b101000001010000010011 5
b101000001010000010011 N
b101000001010000010011 a
b101000001010000010011 c
b1011 d
b101101 /
b101101 h
b101100 2
b101100 e
b101100 j
1"
#170000
0"
