control_unit/control_unit.sv
module control_unit (output logic [1:0] PCSrc, 
                     output logic [1:0] ResultSrc,
                     output logic MemWrite, ALUSrc, RegWrite,
                     output logic [4:0] ALUControl,
                     output logic [2:0] ImmSrc,
                     input logic [31:0] Instr,
                     input logic Zero, Negative);

    logic [6:0] opcode;
    logic [2:0] funct3;
    logic [6:0] funct7;
    
    assign opcode = Instr[6:0];     // Extract opcode
    assign funct3 = Instr[14:12];   // Extract funct3 field
    assign funct7 = Instr[31:25];   // Extract funct7 field

    always_comb begin
        // Default values
        PCSrc = 2'b00;
        ResultSrc = 2'b00;
        MemWrite = 0;
        ALUSrc = 0;
        RegWrite = 1;
        ALUControl = 5'b00000;
        ImmSrc = 3'b000;

        // Additional control signals based on instruction type
        case (opcode)
            7'b0110011: begin // R-type
                RegWrite = 1;
                ALUSrc = 0;
                MemWrite = 0;
                ResultSrc = 2'b01;
                PCSrc = 2'b00;
                ImmSrc = 3'b000;

                // Deciding the operations for the R-type instructions
                case (funct3)
                    3'b000: begin
                        case (funct7)
                            7'b0000000: ALUControl = 5'b00010; // add
                            7'b0100000: ALUControl = 5'b01010; // sub
                            default: ALUControl = 5'b00000;
                        endcase
                    end
                    3'b001: ALUControl = 5'b00000; // sll
                    3'b010: ALUControl = 5'b01001; // slt
                    3'b101: ALUControl = 5'b10000; // srl
                    3'b110: ALUControl = 5'b00111; // or
                    3'b111: ALUControl = 5'b00011; // and
                    default: ALUControl = 5'b00000;
                endcase
            end
        

            7'b0010011: begin // I-type
                RegWrite = 1;
                ALUSrc = 1;
                ImmSrc = 3'b000;
                MemWrite = 0;
                ResultSrc = 2'b01;
                PCSrc = 2'b00;
                
                case (funct3)
                    3'd0: ALUControl = 5'b00010; // addi
                    3'd1: ALUControl = 5'b00000; // slli
                    3'd2: ALUControl = 5'b01001; // slti
                    3'd5: ALUControl = 5'b10000; // srli
                    3'd6: ALUControl = 5'b00111; // ori
                    3'd7: ALUControl = 5'b00011; // andi
                    default: ALUControl = 5'b00000;
                endcase
            end

            7'b0000011: begin // lw
                RegWrite = 1;
                ALUSrc = 1;
                ImmSrc = 3'b000;
                MemWrite = 0;
                ResultSrc = 2'b10;
                ALUControl = 5'b00010; // Add for address calculation
                PCSrc = 2'b00;
            end

            7'b0100011: begin // sw
                RegWrite = 0;
                ALUSrc = 1;
                ImmSrc = 3'b001;
                MemWrite = 1;
                ALUControl = 5'b00010; // Add for address calculation
                PCSrc = 2'b00;
            end

            7'b1100011: begin // B-type
                RegWrite = 0;
                ALUSrc = 0;
                ImmSrc = 3'b010;
                MemWrite = 0;
                ResultSrc = 2'b00;

                case (funct3)
                    3'd0: begin // beq
                        PCSrc = Zero ? 2'b01 : 2'b00;
                        ALUControl = 5'b01010;;
                    end

                    3'd1: begin // bne
                        PCSrc = !Zero ? 2'b01 : 2'b00;
                        ALUControl = 5'b01010;
                    end

                    3'd4: begin
                        PCSrc = Negative ? 2'b01 : 2'b00; // blt
                        ALUControl = 5'b01001;
                    end

                    3'd5: begin
                        PCSrc = !Negative ? 2'b01 : 2'b00; // bge
                        ALUControl = 5'b01001;
                    end
                
                    default: PCSrc = 2'b00;
                endcase
            end


            7'b1101111: begin // jal
                RegWrite = 1;
                ALUSrc = 0;
                ImmSrc = 3'b100;
                MemWrite = 0;
                ResultSrc = 2'b11;
                PCSrc = 2'b01;
                ALUControl = 5'b00000; // Add for address calculation
            end


            7'b1100111: begin // jalr
                RegWrite = 1;
                ImmSrc = 3'b000;
                ALUSrc = 1;
                ALUControl = 5'b00010;
                PCSrc = 2'b10;
                ResultSrc = 2'b11; // Write PC+4 to register
                MemWrite = 0;
            end


            7'b0110111: begin // lui
                RegWrite = 1;
                ALUSrc = 0;
                ImmSrc = 3'b011;
                ResultSrc = 2'b00;
                MemWrite = 0;
                ALUControl = 5'b00010;
                PCSrc = 2'b00;
            end


            default: begin
                PCSrc = 2'b00;
                ResultSrc = 2'b00;
                MemWrite = 0;
                ALUSrc = 0;
                RegWrite = 0;
                ALUControl = 5'b00000;
                ImmSrc = 3'b000;
            end
        endcase
    end

endmodule

control_unit/control_unit_tb.sv
`timescale 1ns/1ps
`include "control_unit.sv"

module control_unit_tb;

// Declare test variables
logic [31:0] t_Instr;
logic t_Zero, t_Negative;
logic [1:0] t_PCSrc, t_ResultSrc;
logic t_MemWrite, t_ALUSrc, t_RegWrite;
logic [4:0] t_ALUControl;
logic [2:0] t_ImmSrc;
// string test_name = "HI";

// Instantiate the module under test (DUT)
control_unit dut(
    .PCSrc(t_PCSrc),
    .ResultSrc(t_ResultSrc),
    .MemWrite(t_MemWrite),
    .ALUSrc(t_ALUSrc),
    .RegWrite(t_RegWrite),
    .ALUControl(t_ALUControl),
    .ImmSrc(t_ImmSrc),
    .Instr(t_Instr),
    .Zero(t_Zero),
    .Negative(t_Negative)
);

// Helper function to display test results
function void display_test(string test_name);
    $display("Time = %3d, Test: %s", $time, test_name);
    $display("  Instr = %8h, Zero = %b, Negative = %b", t_Instr, t_Zero, t_Negative);
    $display("  PCSrc = %b, ResultSrc = %b, MemWrite = %b, ALUSrc = %b, RegWrite = %b", 
              t_PCSrc, t_ResultSrc, t_MemWrite, t_ALUSrc, t_RegWrite);
    $display("  ALUControl = %5b, ImmSrc = %3b", t_ALUControl, t_ImmSrc);
endfunction

initial begin
    // Create a waveform dump file for GTKWave analysis
    $dumpfile("control_unit_tb.vcd");
    $dumpvars(0, control_unit_tb);
    
    // Initialize test inputs
    t_Instr = 32'h00000000;
    t_Zero = 0;
    t_Negative = 0;
    #5;
    
    $display("Starting Control Unit Tests...");

    // Test Case 1: R-type ADD (opcode=0110011, funct3=000, funct7=0000000)
    $display("R-type ADD");
    t_Instr = 32'h00000033; // add x0, x0, x0
    #5;
    
    // Test Case 2: R-type SUB (opcode=0110011, funct3=000, funct7=0100000)
    $display("R-type SUB");
    t_Instr = 32'h40000033; // sub x0, x0, x0
    #5;
    // display_test("R-type SUB");
    
    // Test Case 3: R-type OR (opcode=0110011, funct3=110, funct7=0000000)
    $display("R-type OR");
    t_Instr = 32'h00006033; // or x0, x0, x0
    #5;
    // display_test("R-type OR");
    
    // Test Case 4: R-type AND (opcode=0110011, funct3=111, funct7=0000000)
    $display("R-type AND");
    t_Instr = 32'h00007033; // and x0, x0, x0
    #5;
    // display_test("R-type AND");
    
    // Test Case 5: R-type SLL (opcode=0110011, funct3=001, funct7=0000000)
    $display("R-type SLL");
    t_Instr = 32'h00001033; // sll x0, x0, x0
    #5;
    // display_test("R-type SLL");
    
    // Test Case 6: R-type SLT (opcode=0110011, funct3=010, funct7=0000000)
    $display("R-type SLT");
    t_Instr = 32'h00002033; // slt x0, x0, x0
    #5;
    // display_test("R-type SLT");
    
    // Test Case 7: R-type SRL (opcode=0110011, funct3=101, funct7=0000000)
    $display("R-type SRL");
    t_Instr = 32'h00005033; // srl x0, x0, x0
    #5;
    // display_test("R-type SRL");
    
    // Test Case 8: I-type ADDI (opcode=0010011, funct3=000)
    $display("I-type ADDI");
    t_Instr = 32'h00000013; // addi x0, x0, 0
    #5;
    // display_test("I-type ADDI");
    
    // Test Case 9: I-type SLLI (opcode=0010011, funct3=001)
    $display("I-type SLLI");
    t_Instr = 32'h00001013; // slli x0, x0, 0
    #5;
    // display_test("I-type SLLI");
    
    // Test Case 10: I-type SLTI (opcode=0010011, funct3=010)
    $display("I-type SLTI");
    t_Instr = 32'h00002013; // slti x0, x0, 0
    #5;
    // display_test("I-type SLTI");
    
    // Test Case 11: I-type SRLI (opcode=0010011, funct3=101)
    $display("I-type SRLI");
    t_Instr = 32'h00005013; // srli x0, x0, 0
    #5;
    // display_test("I-type SRLI");
    
    // Test Case 12: I-type ORI (opcode=0010011, funct3=110)
    $display("I-type ORI");
    t_Instr = 32'h00006013; // ori x0, x0, 0
    #5;
    // display_test("I-type ORI");
    
    // Test Case 13: I-type ANDI (opcode=0010011, funct3=111)
    $display("I-type ANDI");
    t_Instr = 32'h00007013; // andi x0, x0, 0
    #5;
    // display_test("I-type ANDI");
    
    // Test Case 14: I-type LW (opcode=0000011)
    $display("I-type LW");
    t_Instr = 32'h00000003; // lw x0, 0(x0)
    #5;
    // display_test("I-type LW");
    
    // Test Case 15: S-type SW (opcode=0100011)
    $display("S-type SW");
    t_Instr = 32'h00000023; // sw x0, 0(x0)
    #5;
    // display_test("S-type SW");

    
    // // Test Case 16a: B-type BEQ with Zero=1 (opcode=1100011, funct3=000)
    $display("B-type BEQ with Zero=1");
    t_Instr = 32'h00000063; // beq x0, x0, 0
    t_Zero = 1;
    t_Negative = 0;
    #5;

    // Test Case 16b: B-type BEQ with Zero=0 (opcode=1100011, funct3=000)
    $display("B-type BEQ with Zero=0");
    t_Instr = 32'h00000063; // beq x0, x0, 0
    t_Zero = 0;
    t_Negative = 0;
    #5;

    // Test Case 17a: B-type BEQ with Zero=1 (opcode=1100011, funct3=000)
    $display("B-type BNE wit Zero=1");
    t_Instr = 32'h00001063; // beq x0, x0, 0
    t_Zero = 1;
    t_Negative = 0;
    #5;

    // Test Case 17b: B-type BEQ with Zero=0 (opcode=1100011, funct3=000)
    $display("B-type BNE wit Zero=0");
    t_Instr = 32'h00001063; // beq x0, x0, 0
    t_Zero = 0;
    t_Negative = 0;
    #5;

    // // Test Case 18a: B-type BEQ with Zero=1 (opcode=1100011, funct3=000)
    $display("B-type BLT with Negative=1");
    t_Instr = 32'h00004063; // beq x0, x0, 0
    t_Zero = 0;
    t_Negative = 1;
    #5;
    
    // // Test Case 18b: B-type BEQ with Zero=1 (opcode=1100011, funct3=000)
    $display("B-type BLT with Negative=0");
    t_Instr = 32'h00004063; // beq x0, x0, 0
    t_Zero = 0;
    t_Negative = 0;
    #5;

    // // Test Case 19a: B-type BEQ with Zero=1 (opcode=1100011, funct3=000)
    $display("B-type BGE with Negative=1");
    t_Instr = 32'h00005063; // beq x0, x0, 0
    t_Zero = 0;
    t_Negative = 1;
    #5;

    // // Test Case 19b: B-type BEQ with Zero=1 (opcode=1100011, funct3=000)
    $display("B-type BGE with Negative=0");
    t_Instr = 32'h00005063; // beq x0, x0, 0
    t_Zero = 0;
    t_Negative = 0;
    #5;
    
    // Test Case 20: J-type JAL (opcode=1101111)
    $display("J-type JAL");
    t_Instr = 32'h0000006f; // jal x0, 0
    t_Zero = 0;
    t_Negative = 0;
    #5;
    // display_test("J-type JAL");
    
    // Test Case 21: I-type JALR (opcode=1100111)
    $display("I-type JALR");
    t_Instr = 32'h00000067; // jalr x0, 0(x0)
    #5;
    // display_test("I-type JALR");
    
    // Test Case 22: U-type LUI (opcode=0110111)
    $display("U-type LUI");
    t_Instr = 32'h00000037; // lui x0, 0
    #5;
    // display_test("U-type LUI");
    
    // Test Case 23: Default case (invalid opcode)
    $display("Invalid instruction");
    t_Instr = 32'h00000000; // Invalid opcode
    #5;
    // display_test("Invalid instruction");
    
    $display("All tests completed.");
    #10;
    $finish;
end

initial begin
    // $monitor("Time = %3d, Test: %s", $time, "test_name");
    // $monitor("  Instr = %8h, Zero = %b, Negative = %b", t_Instr, t_Zero, t_Negative);
    // $monitor("  PCSrc = %b, ResultSrc = %b, MemWrite = %b, ALUSrc = %b, RegWrite = %b", 
    //           t_PCSrc, t_ResultSrc, t_MemWrite, t_ALUSrc, t_RegWrite);
    // $monitor("  ALUControl = %5b, ImmSrc = %3b", t_ALUControl, t_ImmSrc);

    $monitor("Time = %3d, Instr = %8h, Zero = %b, Negative = %b, RegWrite = %b, ImmSrc = %3b, ALUSrc = %b, ALUControl = %5b, MemWrite = %b, ResultSrc = %b, PCSrc = %b", 
             $time, t_Instr, t_Zero, t_Negative, t_RegWrite, t_ImmSrc, t_ALUSrc, t_ALUControl, t_MemWrite, t_ResultSrc, t_PCSrc);
end

// Itype ori is wrin: 00011 instead of XX111

endmodule

control_unit/control_unit_tb.vcd
$date
	Sat Mar 08 23:56:37 2025
$end
$version
	Icarus Verilog
$end
$timescale
	1ps
$end
$scope module control_unit_tb $end
$var wire 2 ! t_ResultSrc [1:0] $end
$var wire 1 " t_RegWrite $end
$var wire 2 # t_PCSrc [1:0] $end
$var wire 1 $ t_MemWrite $end
$var wire 3 % t_ImmSrc [2:0] $end
$var wire 1 & t_ALUSrc $end
$var wire 5 ' t_ALUControl [4:0] $end
$var reg 32 ( t_Instr [31:0] $end
$var reg 1 ) t_Negative $end
$var reg 1 * t_Zero $end
$scope function display_test $end
$upscope $end
$scope module dut $end
$var wire 32 + Instr [31:0] $end
$var wire 1 ) Negative $end
$var wire 1 * Zero $end
$var wire 7 , opcode [6:0] $end
$var wire 7 - funct7 [6:0] $end
$var wire 3 . funct3 [2:0] $end
$var reg 5 / ALUControl [4:0] $end
$var reg 1 & ALUSrc $end
$var reg 3 0 ImmSrc [2:0] $end
$var reg 1 $ MemWrite $end
$var reg 2 1 PCSrc [1:0] $end
$var reg 1 " RegWrite $end
$var reg 2 2 ResultSrc [1:0] $end
$upscope $end
$upscope $end
$enddefinitions $end
$comment Show the parameter values. $end
$dumpall
$end
#0
$dumpvars
b0 2
b0 1
b0 0
b0 /
b0 .
b0 -
b0 ,
b0 +
0*
0)
b0 (
b0 '
0&
b0 %
0$
b0 #
0"
b0 !
$end
#5000
b10 '
b10 /
b1 !
b1 2
1"
b110011 ,
b110011 (
b110011 +
#10000
b1010 '
b1010 /
b1 !
b1 2
b100000 -
b1000000000000000000000000110011 (
b1000000000000000000000000110011 +
#15000
b111 '
b111 /
b1 !
b1 2
b110 .
b0 -
b110000000110011 (
b110000000110011 +
#20000
b11 '
b11 /
b1 !
b1 2
b111 .
b111000000110011 (
b111000000110011 +
#25000
b0 '
b0 /
b1 !
b1 2
b1 .
b1000000110011 (
b1000000110011 +
#30000
b1001 '
b1001 /
b1 !
b1 2
b10 .
b10000000110011 (
b10000000110011 +
#35000
b10000 '
b10000 /
b1 !
b1 2
b101 .
b101000000110011 (
b101000000110011 +
#40000
1&
b10 '
b10 /
b1 !
b1 2
b10011 ,
b0 .
b10011 (
b10011 +
#45000
b0 '
b0 /
1&
b1 !
b1 2
b1 .
b1000000010011 (
b1000000010011 +
#50000
b1001 '
b1001 /
1&
b1 !
b1 2
b10 .
b10000000010011 (
b10000000010011 +
#55000
b10000 '
b10000 /
1&
b1 !
b1 2
b101 .
b101000000010011 (
b101000000010011 +
#60000
b111 '
b111 /
1&
b1 !
b1 2
b110 .
b110000000010011 (
b110000000010011 +
#65000
b11 '
b11 /
1&
b1 !
b1 2
b111 .
b111000000010011 (
b111000000010011 +
#70000
b10 '
b10 /
1&
b10 !
b10 2
b11 ,
b0 .
b11 (
b11 +
#75000
1$
b1 %
b1 0
0"
b10 '
b10 /
1&
b0 !
b0 2
b100011 ,
b100011 (
b100011 +
#80000
b1 #
b1 1
b10 %
b10 0
b1010 '
b1010 /
0"
0&
0$
b1100011 ,
1*
b1100011 (
b1100011 +
#85000
b10 %
b10 0
b1010 '
b1010 /
0"
b0 #
b0 1
0*
#90000
b10 %
b10 0
b1010 '
b1010 /
0"
b1 .
1*
b1000001100011 (
b1000001100011 +
#95000
b1 #
b1 1
b10 %
b10 0
b1010 '
b1010 /
0"
0*
#100000
b10 %
b10 0
b1001 '
b1001 /
0"
b1 #
b1 1
b100 .
1)
b100000001100011 (
b100000001100011 +
#105000
b10 %
b10 0
b1001 '
b1001 /
0"
b0 #
b0 1
0)
#110000
b10 %
b10 0
b1001 '
b1001 /
0"
b101 .
1)
b101000001100011 (
b101000001100011 +
#115000
b1 #
b1 1
b10 %
b10 0
b1001 '
b1001 /
0"
0)
#120000
b11 !
b11 2
b100 %
b100 0
b0 '
b0 /
1"
b1 #
b1 1
b1101111 ,
b0 .
b1101111 (
b1101111 +
#125000
b10 '
b10 /
1&
b0 %
b0 0
b11 !
b11 2
b10 #
b10 1
b1100111 ,
b1100111 (
b1100111 +
#130000
b11 %
b11 0
b10 '
b10 /
0&
b0 !
b0 2
b0 #
b0 1
b110111 ,
b110111 (
b110111 +
#135000
0"
b0 %
b0 0
b0 '
b0 /
b0 ,
b0 (
b0 +
